tapioca_statuspage/__init__.py
tapioca_statuspage/resource_mapping.py
tapioca_statuspage/tapioca_statuspage.py
tapioca_statuspage-0.0.3.dist-info/DESCRIPTION.rst
tapioca_statuspage-0.0.3.dist-info/METADATA
tapioca_statuspage-0.0.3.dist-info/RECORD
tapioca_statuspage-0.0.3.dist-info/WHEEL
tapioca_statuspage-0.0.3.dist-info/metadata.json
tapioca_statuspage-0.0.3.dist-info/top_level.txt
