Metadata-Version: 2.0
Name: tapioca-statuspage
Version: 0.0.3
Summary: StausPage.io wrapper using tapioca
Home-page: https://github.com/olist/tapioca-statuspage
Author: Olist Developers
Author-email: developers@olist.com
License: MIT
Keywords: statuspage
Platform: UNKNOWN
Classifier: Development Status :: 5 - Production/Stable
Classifier: Intended Audience :: Developers
Classifier: License :: OSI Approved :: MIT License
Classifier: Natural Language :: English
Classifier: Programming Language :: Python :: 3.5
Requires-Dist: tapioca-wrapper (==1.4.2)
